django_spellbook/__init__.py
django_spellbook/apps.py
django_spellbook/django_spellbook.py
django_spellbook/parsers.py
django_spellbook/sitemaps.py
django_spellbook/spellblocks.py
django_spellbook/urls.py
django_spellbook/utils.py
django_spellbook/views.py
django_spellbook/blocks/__init__.py
django_spellbook/blocks/base.py
django_spellbook/blocks/exceptions.py
django_spellbook/blocks/registry.py
django_spellbook/management/__init__.py
django_spellbook/management/commands/__init__.py
django_spellbook/management/commands/__private.py
django_spellbook/management/commands/command_utils.py
django_spellbook/management/commands/spellbook_md.py
django_spellbook/management/commands/spellbook_validate.py
django_spellbook/management/commands/spellbook_wizard.py
django_spellbook/management/commands/wizard_utils.py
django_spellbook/management/commands/processing/__init__.py
django_spellbook/management/commands/processing/directory_index.py
django_spellbook/management/commands/processing/file_processor.py
django_spellbook/management/commands/processing/file_writer.py
django_spellbook/management/commands/processing/generator_utils.py
django_spellbook/management/commands/processing/manifest.py
django_spellbook/management/commands/processing/navigation.py
django_spellbook/management/commands/processing/template_generator.py
django_spellbook/management/commands/processing/url_generator.py
django_spellbook/management/commands/processing/url_view_generator.py
django_spellbook/management/commands/processing/view_generator.py
django_spellbook/management/commands/spellbook_md_p/__init__.py
django_spellbook/management/commands/spellbook_md_p/discovery.py
django_spellbook/management/commands/spellbook_md_p/exceptions.py
django_spellbook/management/commands/spellbook_md_p/processor.py
django_spellbook/management/commands/spellbook_md_p/reporter.py
django_spellbook/management/commands/wizard/__init__.py
django_spellbook/management/commands/wizard/validate.py
django_spellbook-0.2.4.dist-info/licenses/LICENSE
django_spellbook-0.2.4.dist-info/METADATA
django_spellbook-0.2.4.dist-info/WHEEL
django_spellbook-0.2.4.dist-info/top_level.txt
django_spellbook-0.2.4.dist-info/RECORD
