Metadata-Version: 2.4
Name: django-spellbook
Version: 0.2.4
Summary: A Django library for creating and managing content blocks in markdown for developers and bloggers
Home-page: https://github.com/smattymatty/django_spellbook
Author: Mathew Storm
Author-email: mathewstormdev@gmail.com
License: MIT
Project-URL: Documentation, https://django-spellbook.org/
Project-URL: Bug Reports, https://github.com/smattymatty/django_spellbook/issues
Project-URL: Source, https://github.com/smattymatty/django_spellbook
Classifier: Development Status :: 3 - Alpha
Classifier: Framework :: Django
Classifier: Framework :: Django :: 5.0
Classifier: Intended Audience :: Developers
Classifier: Programming Language :: Python :: 3.10
Classifier: Operating System :: OS Independent
Classifier: Topic :: Software Development :: Libraries :: Python Modules
Requires-Python: >=3.10
License-File: LICENSE
Requires-Dist: django>=5.0
Requires-Dist: markdown>=3.0
Requires-Dist: pyyaml>=6.0
Dynamic: author
Dynamic: author-email
Dynamic: classifier
Dynamic: description
Dynamic: description-content-type
Dynamic: home-page
Dynamic: license
Dynamic: license-file
Dynamic: project-url
Dynamic: requires-dist
Dynamic: requires-python
Dynamic: summary
